PiQR/PiQR.py
PiQR/__init__.py
PiQR/conversions.py
PiQR/data_analysis.py
PiQR/error_correction.py
PiQR/qr_coords.py
PiQR/qr_imager.py
PiQR/qr_masks.py
PiQR/qr_penalty.py
PiQR/qr_ps.py
PiQR/qr_shapes.py
PiQR/setup.py
piqr-0.1.6.dist-info/licenses/LICENSE
piqr-0.1.6.dist-info/METADATA
piqr-0.1.6.dist-info/WHEEL
piqr-0.1.6.dist-info/top_level.txt
piqr-0.1.6.dist-info/RECORD
