Metadata-Version: 2.4
Name: PiQR
Version: 0.1.6
Summary: A Python library for generating and displaying QR codes.
Author-email: PimpDiCaprio <info@aperturesoftware.us>
Project-URL: Homepage, https://github.com/PimpDiCaprio/PyQR
Project-URL: Issues, https://github.com/PimpDiCaprio/PyQR/issues
Classifier: Programming Language :: Python :: 3
Classifier: License :: OSI Approved :: MIT License
Classifier: Operating System :: OS Independent
Requires-Python: >=3.8
License-File: LICENSE
Dynamic: license-file
